mygrad/__init__.py
mygrad/_dtype_mirrors.py
mygrad/_io.py
mygrad/_numpy_version.py
mygrad/_version.py
mygrad/computational_graph.py
mygrad/errors.py
mygrad/operation_base.py
mygrad/py.typed
mygrad/tensor_base.py
mygrad/_tensor_core_ops/__init__.py
mygrad/_tensor_core_ops/indexing.py
mygrad/_utils/__init__.py
mygrad/_utils/duplicating_graph.py
mygrad/_utils/graph_tracking.py
mygrad/_utils/lock_management.py
mygrad/indexing_routines/__init__.py
mygrad/indexing_routines/funcs.py
mygrad/indexing_routines/ops.py
mygrad/linalg/__init__.py
mygrad/linalg/funcs.py
mygrad/linalg/ops.py
mygrad/math/__init__.py
mygrad/math/_special.py
mygrad/math/consts.py
mygrad/math/nondifferentiable.py
mygrad/math/arithmetic/__init__.py
mygrad/math/arithmetic/funcs.py
mygrad/math/arithmetic/ops.py
mygrad/math/exp_log/__init__.py
mygrad/math/exp_log/funcs.py
mygrad/math/exp_log/ops.py
mygrad/math/hyperbolic_trig/__init__.py
mygrad/math/hyperbolic_trig/funcs.py
mygrad/math/hyperbolic_trig/ops.py
mygrad/math/misc/__init__.py
mygrad/math/misc/funcs.py
mygrad/math/misc/ops.py
mygrad/math/sequential/__init__.py
mygrad/math/sequential/funcs.py
mygrad/math/sequential/ops.py
mygrad/math/trigonometric/__init__.py
mygrad/math/trigonometric/funcs.py
mygrad/math/trigonometric/ops.py
mygrad/nnet/__init__.py
mygrad/nnet/activations/__init__.py
mygrad/nnet/activations/elu.py
mygrad/nnet/activations/glu.py
mygrad/nnet/activations/hard_tanh.py
mygrad/nnet/activations/leaky_relu.py
mygrad/nnet/activations/relu.py
mygrad/nnet/activations/selu.py
mygrad/nnet/activations/sigmoid.py
mygrad/nnet/activations/soft_sign.py
mygrad/nnet/activations/softmax.py
mygrad/nnet/initializers/__init__.py
mygrad/nnet/initializers/constant.py
mygrad/nnet/initializers/dirac.py
mygrad/nnet/initializers/glorot_normal.py
mygrad/nnet/initializers/glorot_uniform.py
mygrad/nnet/initializers/he_normal.py
mygrad/nnet/initializers/he_uniform.py
mygrad/nnet/initializers/normal.py
mygrad/nnet/initializers/uniform.py
mygrad-2.3.0.dist-info/LICENSE.txt
mygrad-2.3.0.dist-info/METADATA
mygrad-2.3.0.dist-info/WHEEL
mygrad-2.3.0.dist-info/top_level.txt
mygrad-2.3.0.dist-info/RECORD
