Metadata-Version: 2.1
Name: mygrad
Version: 2.3.0
Summary: Drop-in automatic differentiation to NumPy
Author-email: Ryan Soklaski <rsoklaski@gmail.com>
Maintainer-email: Ryan Soklaski <rsoklaski@gmail.com>
License: MIT
Project-URL: Homepage, https://mygrad.readthedocs.io/en/latest/
Project-URL: Bug Reports, https://github.com/rsokl/MyGrad/issues
Project-URL: Source, https://github.com/rsokl/MyGrad
Classifier: Development Status :: 5 - Production/Stable
Classifier: License :: OSI Approved :: MIT License
Classifier: Operating System :: OS Independent
Classifier: Intended Audience :: Science/Research
Classifier: Intended Audience :: Education
Classifier: Programming Language :: Python
Classifier: Programming Language :: Python :: 3
Classifier: Programming Language :: Python :: 3.9
Classifier: Programming Language :: Python :: 3.10
Classifier: Programming Language :: Python :: 3.11
Classifier: Programming Language :: Python :: 3.12
Classifier: Topic :: Scientific/Engineering
Requires-Python: >=3.9
License-File: LICENSE.txt
Requires-Dist: numpy!=1.25.0,>=1.24
Requires-Dist: typing-extensions!=4.6.0,>=4.1.0
Provides-Extra: rnn
Requires-Dist: numba>=0.34.0; extra == "rnn"
Provides-Extra: test
Requires-Dist: pytest>=3.8; extra == "test"
Requires-Dist: hypothesis>=6.17.1; extra == "test"
Requires-Dist: scipy; extra == "test"
